{"timeSaved":1649327367.0958002,"options":{"brightAddRed":20.058,"brightAddGreen":19.958,"brightAddBlue":48.763,"brightMult":71.068,"accelFieldMul":1974905005817,"bootShapeY":0.011,"bootShapeX":0.01,"bootShapeScale":0.951,"nearPdist":0.373,"friction":0,"loopSeconds":25.801,"useTimePosition":true,"timePosition":33.442,"timePositionDecay":0.168,"timeSpeed":1.599,"minPointsPerCurve":56,"maxPointsPerCurve":813,"maxNumPointsPerCurveChangeAtOnce":74,"borderFraction":0.66,"maxSpeed":0.043,"targetDistanceBetweenAdjacentCurvePoints":0.009,"maxCurvesPerReef":10000,"scalePotentialEnergyForce":3757329.05,"ampStraightIfNear":2900654394.558,"maxDistanceToAffectEachother":0.092,"addRandomness":6474500.766,"stayInsideBorderCircleForce":-10742213890.948,"distanceScale":0.037,"pause":false,"attractIfFartherThan":0.4,"ampAttractIfFartherThan":1.726,"graphEndist":true,"isSurface":true,"displayOuterCircle":true,"ifCanvasUseUndoGraphics":true,"negTimeDoesUndo":true,"autoMoveTimeSpeedSlider":false,"balanceSparsity":true,"onlyEndist":false,"setSpeedsToZeroAfterEveryDtMove":false,"freqA":52.287,"ampA":29524.714,"freqB":5.441,"ampB":7884253.866,"freqC":20.452,"ampC":271917.345,"midDist":0.056,"bellAAveMul":0.375,"bellADevMul":0.147,"bellAHeight":2160910996.894,"bellBAveMul":0.176,"bellBDevMul":7.453,"bellBHeight":1262130245285.963,"bellCAveMul":1.332,"bellCDevMul":1.028,"bellCHeight":-207327208.042,"forceMaxResolution":true,"stretchToWindow":true,"canvasElseSvg":true,"isEraseCanvasEachFrame":true,"repelSelf":49280.617,"repelSelfDistance":40.162,"computeSpeed":1.28,"colorSeed":93245455553395,"colorDecayPerSec":0.643,"endist":"(en,dist,pdist)=>{ let x = 0; let p = o; let nd = p.nearPdist; let near = sigmoid(-5*(dist-nd)); if(dist > o.attractIfFartherThan) x += o.ampAttractIfFartherThan*sqr(dist-o.attractIfFartherThan); x += o.ampStraightIfNear*near*sqr(dist-pdist); let midDist = p.midDist; x += bell(midDist*p.bellAAveMul,midDist*p.bellADevMul,p.bellAHeight,dist); x += bell(midDist*p.bellBAveMul,midDist*p.bellBDevMul,p.bellBHeight,dist); x += bell(midDist*p.bellCAveMul,midDist*p.bellCDevMul,p.bellCHeight,dist); let m=dist*twoPi; x += sin(m*p.freqA)*p.ampA; x += sin(m*p.freqB)*p.ampB; x += sin(m*p.freqC)*p.ampC; x += en; return x; }","isOnlyMoveRandomlyPerpendicularToSurface":false,"graphEndistBright":"Math.sqrt","bootShape":"a=>.2","paintBrightAdd":3,"lineThick":1,"paintBrightMult":0.999,"brightMultRed":1.01,"brightMultGreen":1.01,"brightMultBlue":1.01,"sameColorness":0.01,"wrapPaintBrightMult":true,"accelVoxels":[],"loops":{"timePosition":[0.184,0.128,0.127,0.363,0.472,0.532,0.638,0.753,0.912,0.875,0.736,0.46,2.983,0.381,0.555,0.8,1.072,1.304,1.082,0.912,1.286,1.542,1.065,0.957,1.389,1.342,1.115,0.882,0.597,0.368,0.349,0.158],"midDist":[1.088,1.549,0.983,0.63,0.98,1.094,0.989,1.195,1.104,0.58,0.776,1.517,1.312,0.526,0.682,1.316,1.212,0.89,0.988,0.921,0.765,1.192,1.451,0.787,0.433,1.156,1.535,0.929,0.64,1.008,1.084,0.994],"bellAAveMul":[1.088,0.624,0.989,0.748,1.57,0.974,0.887,0.793],"bellADevMul":[1.088,0.758,1.115,1.212,0.529,1.449,0.796,0.997],"bellBAveMul":[1.088,0.744,1.114,1.226,0.554,1.349,0.928,0.935],"bellBDevMul":[1.088,0.761,1.116,1.208,0.526,1.468,0.768,1.013],"bellCAveMul":[1.088,0.828,1.101,1.12,0.605,1.574,0.444,1.338],"bellCDevMul":[1.088,0.643,1.035,1.075,1.372,0.447,1.159,0.964],"accelFieldMul":[1.088,1.556,1.103,0.632,0.844,1.113,1.015,1.051,1.241,0.968,0.534,0.851,1.525,1.358,0.604,0.551,1.17,1.344,0.994,0.903,1.013,0.846,0.803,1.262,1.44,0.821,0.409,0.975,1.549,1.197,0.656,0.79],"freqB":[1.088,1.815,1.125,1.532,0.446,1.52,0.79,1.905],"maxPointsPerCurve":[0.252,0.229,0.264,0.319,0.753,0.625,0.794,1.031,1.115,1.042,0.623,0.458,0.324,0.34,0.456,0.787,1.069,1.123,0.859,0.933,1.373,1.445,1.235,1.309,1.409,1.213,1.123,0.726,0.328,0.395,0.337,0.266],"paintBrightMult":[1.088,1.669,1.527,0.781,1.148,0.75,1.325,0.216,0.621,1.672,0.749,0.472,1.026,1.103,1.11,0.245,1.014,0.986,-0.421,1.08,1.169,1.233,1.228,0.003,0.964,-0.284,0.595,0.522,0.582,0.615,0.136,1.324,1.527,1.593,-0.241,1.263,0.149,0.837,0.779,0.538,0.546,0.558,1.337,0.939,-0.146,0.605,0.319,1.128,0.99,-0.188,0.773,0.975,0.977,0.61,0.331,0.008,1.414,0.772,0.842,0.907,1.027,0.204,0.762,0.62]},"name":"evo_thin branches_evo_shouldwe__3d_coral_100_unusedHIllsRemoved 661 _small 529","dir":"3"}}