{"timeSaved":1646848352.8151002,"options":{"bootShapeY":0.03,"bootShapeX":0.01,"bootShapeScale":1,"nearPdist":0.063,"friction":0,"loopSeconds":34.298,"useTimePosition":true,"timePosition":17.616,"timePositionDecay":0.292,"timeSpeed":1.171,"minPointsPerCurve":61,"maxPointsPerCurve":507,"maxNumPointsPerCurveChangeAtOnce":117,"borderFraction":0.663,"maxSpeed":0.054,"targetDistanceBetweenAdjacentCurvePoints":0.01,"maxCurvesPerReef":10000,"scalePotentialEnergyForce":20368.795,"ampStraightIfNear":14456035438.35,"maxDistanceToAffectEachother":0.108,"addRandomness":7025396.286,"stayInsideBorderCircleForce":5361433391626.719,"distanceScale":0.023,"pause":false,"attractIfFartherThan":0.4,"ampAttractIfFartherThan":12.473,"graphEndist":true,"isSurface":false,"displayOuterCircle":true,"ifCanvasUseUndoGraphics":true,"negTimeDoesUndo":true,"autoMoveTimeSpeedSlider":false,"balanceSparsity":true,"onlyEndist":false,"setSpeedsToZeroAfterEveryDtMove":false,"freqA":59.975,"ampA":57299.828,"freqB":6.72,"ampB":118569,"freqC":23.198,"ampC":239472.374,"midDist":0.042,"bellAAveMul":0.456,"bellADevMul":0.318,"bellAHeight":17900315279.515,"bellBAveMul":-0.575,"bellBDevMul":0.353,"bellBHeight":30995780070023.254,"bellCAveMul":2.549,"bellCDevMul":9.317,"bellCHeight":-360478210.052,"forceMaxResolution":true,"stretchToWindow":true,"canvasElseSvg":true,"isEraseCanvasEachFrame":true,"repelSelf":49280.617,"repelSelfDistance":40.162,"computeSpeed":1.291,"colorSeed":32414001114555,"colorDecayPerSec":1.062,"endist":"(en,dist,pdist)=>{ let x = 0; let p = o; let nd = p.nearPdist; let near = sigmoid(-5*(dist-nd)); if(dist > o.attractIfFartherThan) x += o.ampAttractIfFartherThan*sqr(dist-o.attractIfFartherThan); x += o.ampStraightIfNear*near*sqr(dist-pdist); let midDist = p.midDist; x += bell(midDist*p.bellAAveMul,midDist*p.bellADevMul,p.bellAHeight,dist); x += bell(midDist*p.bellBAveMul,midDist*p.bellBDevMul,p.bellBHeight,dist); x += bell(midDist*p.bellCAveMul,midDist*p.bellCDevMul,p.bellCHeight,dist); let m=dist*twoPi; x += sin(m*p.freqA)*p.ampA; x += sin(m*p.freqB)*p.ampB; x += sin(m*p.freqC)*p.ampC; x += en; return x; }","brightAddRed":20,"brightAddGreen":20,"brightAddBlue":50,"brightMult":90,"accelFieldMul":89415464119,"isOnlyMoveRandomlyPerpendicularToSurface":false,"graphEndistBright":"Math.sqrt","bootShape":"a=>.2","accelVoxels":[],"loops":{"timePosition":[0.184,0.131,0.127,0.363,0.472,0.532,0.638,0.753,0.912,0.876,0.737,0.46,0.317,0.382,0.555,0.801,1.072,1.304,1.082,0.913,1.286,1.542,1.065,0.957,1.389,1.342,1.115,0.882,0.597,0.368,0.349,0.158]},"name":"twincells","lineThick":1,"paintBrightMult":0.999,"dir":"1"}}