{"721":{"e09e4f4217669b7f735b7a3724e835d8d6344db128eb03d6ea72885e":{"GeneReef0044":{"backgroundColor":"#143544","colorSeed":"72141777838279","files":[{"mediaType":"text/html","name":"GeneReef0044","src":["data:text/html,<html><head><script>let%20code='%5c'use%20strict%","5c';sLo={fB:393358174494155400,rO:[-0.366,-0.3,0.19kZ,0.237wJ24k","Z],gC:2133964.584,ampA:23600.957,eE:0.316,ampB:26825807183686.69",",ampC:-1586686.571,kD:1649206962742.434,ayH:0.4,autoMoveTkPSlide","rnTqIsTbellAhK:0.377oGArG0.297oGArH:-74703966959554.94oGBhK:0.23","5oGBrG0.259oGBrH:264398104377870750oGChK:1.043oGCrG1.529oGCrH:15","8616800838343.28,gA:%5c'%20a=>[%20oE3.2+a*.23))*.5+.3,oEa/5))/2-",".3%20]%5c',gAScale:0.46,gAXdIgAYdIgX:0.25,dZ:68,bwYkU:53,mB:20,b","pJ:0,bpJBluebCkUbCRed:1.01,csNElseSvgsTwM:0.849,chE:721417778382","79,tF:1.259,dir:%5c'4%5c',pQsTaV:0.333,nV:%5c'(en,dist,pdist)=>{","%20let%20x%20=%200aMp%20=%20oaMnd%20=%20p.nZaMnear%20=%20jT(-5*(","dist-nd));%20if(dist%20>%20jYzPo.eEcOjY;zPo.kD*nearcOpxOwH%20=%2","0p.wH;zPbell(eJAcLAaBAoDBcLBaBBoDCcLCaBCrH,xOm=dist*dGfIAuWAfIBu","WBfICuWC;zPen;%20vSx;%20}%5c',forceMaxResolupFTfreqA:44.945,freq","B:10.006,freqC:23.724,pX:0,xYsTxYBright:%5c'uF%5c',oVsTisEraseCs","NEachFramesTisOnlyMoveRandomlyPerpendicularToSurfacenTtDsTlineTh","ick:1,iO:37.564,oL:{fB:[0.fK6,-1.398,-1.8fKhH738,-1.357,jL2.737,","2.76iR61,-0.121,1.83wS11,-1.216,1.602]oGAuO624mUpN48,1.57voY8hM9","3]oGAtH758wF212tLqG4pN96,0.997]oGBuO744lT4,1.2kM554,1.34hIcP935]","oGBtH761lT6,1.208tL6,1.46wS68lV3]oGCuO828,1.101,1.12sG1.57zR44dO","8]oGCtH643cZ5eB5,1.3iD447,1.15hI64]bV[0.252,0.229,0.264,0.31pN53","gV5,0.794cZ1wF042gV3,0.458,0.324,0.3zRsC78iT69dF85hI33,1.373,1.4","45,1.235,1.30qG09,1.213dF7kM3cP395,0.337,0.266],wHdX42,0.634lViT","aA58,0.9rW55qG92,1.04,0.511dO4cZ4,0.9sC87hI27]gR[0.307,0.321,0.3","51,0.402,0.485wJ7,0.8sC825,1.006,0.916,0.518,0.238,0.4kM58hM57,1",".1vG195bU88iT77qXaA33mU1dOaA6iT4hMkM483,0.282,0.2rW3],psUdX669,1",".52hM81,1.14wS5qX5,0.216gV1,1.6iD749,0.472,1.026,1.103lT,0.245lV","4mU6,-jL1.vG169,1.233,1.2cP003,0.964,-0.284,0.595tL2,0.582,0.615",",0.136qX4,1.527,1.593,-0.241,1.263,0.149,0.83hM79,0.538,0.546,0.","558dO7,0.93iR146sG0.319,1.1cP9iR18wS73vV5vV7,0.61,0.331,0.0vG414",",0.7iD842,0.90iT27,0.204,0.762gV],tyLdX5hH365,0.851goYhH09eB6mU6",",1.091,1.24eB9,0.6iD543vV,1.5vG4rW92zR64gV5,1.1hH375,1.167bU92lV","3bU75hI13qX,1.459,1.041]},vF:10000,uI:0.075,vB:64bV874,cK:0.044,","wH:0.064gR91,name:%5c'jU_S19E2_megamegareef%5c',nZ:0.113,jPsTvWn","TpR:3,psU:0.999,pausenTeU:49280.617,eUDistance:40.162,oCdIeV:252","01720560.367,mEnTuV:1.7140345825040882e+22,stretchToWindowsTiA:0",".004,tyL:24.78,gT:0.373,tkP:1.604,kVThWsTkY:1.3}cAbxE=falsecAsee","d=uTcW.of(0n)cAzZ=ssslLuT(sss)^zOdN;}cAfM=jNlLnL*zOn+0xBdNfXtQ=(","nL>>(48n-uT(jN)));vSNbT(tQ)|0;}cAcRbHfM(31)/0x8cD00;%20uU%5c'jU:","%20Some%20code%20from%20opensourceMIT%20https://github.com/benra","yfield/augmentedballs%5c')xVsLomV%5c'No%20o/oppF%5c'xVuP%5c'no%2","0nV%5c'cAtgDemQ;eIbuboot()yKUrlParams(),sLoo={},oo.nV=o.nV,oo.oL","=e(o.oL||{}),eval(%5c'uUJSON.sqRify(oo));%5c')cApKBit={},uC={};g","YsXe=o[t];fN=!1===e||!0===e,uC[t]=NbT.isInteger(e),(fN||%5c'nbT%","5c'cVe)&&(ohGo[t])}var%20ibH56+200*cR(),r=(t,e,rkFszGnzGlzGh=oo.","lR,anYst(t,ebJ);if(r)iChpVa.aG[t]=h[t];vSa},sbH{gYo)o.lR?(lR||(n","A.lRbB)),hGlR.wD()):hGoo[t]}qFrocNround,mncNmin,mxcNmax,sincNsin",",coscNcos,wi=window,px=%5c'px%5c',flsW,ctX,n=t=>new%20FloatcW(t)",",l=t=>uYcAh=0,a=350,u=850,p=100,d=600,c=60qFf=0,v=1,b=2,y=3,m=4c","AxjFpH=iEcreateyJ(%5c'csN%5c'),gHgDaTgDkBgDgLyFgDt.appendChild(p","H)fXe=pHmGqZ=10oJ=10,e.position=%5c'absolute%5c',e.left=%5c'0px%","5c',e.top=%5c'0px%5c',e.zIndex=-lZiKtPvJt&&(teQe&&(eiQWidth)),vJ","i&&(ieQr&&(riQrH))fXs=e-t,n=r-i,l=pH,h=lmGcC%5c'hP%5c',n+px),cC%","5c'width%5c',s+px),h.hP=nyYwidth=syYtop=iyYleft=t+px},gLeGoP=pH.","getContext(%5c'2d%5c'),aT=gH.gerJ0,0pZ,qZ)pZoJ)),kB=aT.data,gLyF","nYg(kBoJ,qZ)},gLaJoP.purJaT,0,0)},gLiK(0,10,0,10),gLeG()},gaOt,e",",i){gLb=t,gLh=e,gLw=i},M=gfXP=McG;P.fRRGBAxLs,n){vJn&&(n=255)fXl","yG4*(ro(t)*gLw+ro(e)),gLbbB-4);ePf]=i,ePv]=r,ePb]=s,ePy]=n}qFwwV","2,38),S=16383,A=1<<24;hXYeDwuGeDAuGorReduJ16wQkUuJ8wQBlue=(t=>25","5&t),wZ=(jZ)=>((t&S)<<14|e&S)*A+((255&i)<<16|(255&r)<<8|255&s)),","P.fRUuMhBhXY(t),i=hXX(t),rnWRed(t),snWkU(t),nnWBlue(t);gLhNdE},P",".bMjFwA+)gLfRUuMvYP.uuMaY;vSwZ(t,e,i^fVf],r^fVv],s^fVb])},P.hNaY",";fVf]^=i,fVv]^=r,fVb]^=s,fVbX,PqQaOnQ,asXu=r-e,p=s-i,dcXu,p),ccN","rZd),f=-1,v=-1,b=e,y=i;aIa;e++){aIcbWi=ro(b+u*e/c),r=ro(y+p*e/c)",";i==f&&r==v||(t(gLuuM(i,r,n,l,h)),f=i,v=r)}b+=p/d,y+=u/d}}qFC=jZ","kFl=n(i*s)lBi;n++)vThzHr;l++)h+=t[n*r+l]*e[l*s+i];l[n*s+i]=h}vSl","}cARrCt[0];kKi=1;i<tbB;i++)e*=t[i];vSe},BaOt,e){if(gLsizes=t,e)i","f(%5c'function%5c'cVe){gN;iCmPpVgLhQ=e()}wImP=e;wIgN};BcGqNjFvSy","VeNhC],C(mP,t.arr,eNgLvO1],hC))}cAFrC[];vSetZ...t),e},DuRt;iCepV","{r=rqN(e[t]);iCr.arrpVr.hQ=i(r.hQ)}vSr}qFjT=t=>.5+.5*dAtanh(.5*t",")cAOrCt.vO0],i=hC,r=e-1;aIiiZ.arr[r*i+e]=e==i-1?100:0}qFXkJ_=!_s","pEi=0;do{i=(tsQt+(esQe}while(i>=1||0==i)fXrgU-2*dAlog(i)/i);vSj=","t*r,e*r}vSj},V=(t,e)=>bZ(t*t+e*e))oG=(gS)=>i*bZsqr((r-t)/e)),T=t","=>yAcR()*t)cANcNtanh,E=5,G=1+2*E,I=3,z=G*I+1,U=I,YsSO(t)},ksSwA+",")YvYL=[z,dArZz),U],JpYqFdG=2*dAPI,qxI%5c'xZtiming.navigationStar","t%5c'),HbH.001*(q+xZnow()),WcM)=>mScA_=!1,j=0qFZ=t=>iEgetyJById(","t)cAK=l(1<<21),QmTWfFtdWr=WfFedWs=fl(i)<<11|fl(r)<<1;tJ{y:K[s],x",":K[s+1]}},fSsSiCKpVK[t]=0;wA=6)$(t[elN1lN2lN3lN4lN5])},$=jZ,nkFl","=ce(4*(256*i)),h=etfFtxJ,a=etfFexJ;kKt=h-l;t<h+l;t++)kKe=a-l;e<a","+lbWl=2097151&(t<<11|e<<1),u=l+1,p=(t-hiPd=(e-aiPc=V(p,d),fmX+pt",",dlJvmX,d+ptlJb=2.5;K[lmKlqOs+f)*b,K[umKuqOn+v)*b}}fXttxLuI,gC,c","K,pX,s,h,a,u){if(!smV%5c'no%20points%5c'fXp=e;if(tmV%5c'zYd%20co","de%5c';{let%20t=o.fB;gLdt=ifXe=daPiXY,c=e.iXX,y=e.aG,m=y*o.kY;gL","eYgLkC=sfXxwVgJ2);if(i=mx(-.9,mn(i,.9)),gLypfUxpfUyvfUxvfUredkAp","WkAkTkApsXt=yV1,z]),e=p,n=p.mW(),ukAy=l(s);iCsbOe=nH%25s,i=lDe]-","lDt],ruQ[ebAt],ncXi,r);uxX1:i/n,yxX0:r/n}let%20gzHs;l++){lDl]=p.","hU=p.xp[l],l>0&&(g+cXp.yp[bRl-1],p.cFl-1]));aIGbWi=(e+l-E+s)%25s",";t.arr[3*e+fpLqEv]=ppTqEbmM[i]/127.5-1}rN=1fXM=D(t,h,a),PkSf]),w","kSv]),SkSb]),A=aHo.wM*i,1));lY[lpLyUP,pW[l]=ppTyUw,kT[lmMyUSfXC=","0,R=0,B=i*o.eV,F=Q(gLhU);CeFy,ReFx;iCe.kCbOi=lDbRt],s=gLcFt],h=i","*i+s*smCh&&h<=xsXi=t/e.kC*n,s=mn(oA-g),oA+n-g)),a=u[l],p=y[l],f=","u[t],v=y[t],bgUh),x=1-b/uI,MeAdUiHP=r(lDl]-pt/2sFl],e.yp[t]+pt/2",",e.xp[t]iHweA-pt/2dU+pt/2iHS=(PfQ,A=(wfQ;C+=S*B,R+=A*B}}let%20O=","gC*uF(oA))mCgCsXt=(l+1)%25s,e=lDt]-lDl],iuQ[tbAl],rcXe,i)mCrsXt=","e/r,s=i/r,n=s,l=-t,h=O*X();C+=n*h,R+=l*h}}aC=p.yv[l]+C,oU=p.xv[l","]+RfXVcXaC,oU)mCVsXt=aHV-pX*i,o.cK)),e=t/V;aC*=e,oU*=e}lDl]+=aC*","isFl]+=oU*i,o.mE&&(oU=aC=0)}}epEr=i*gC,n=0,gAxIo.gAYX||o.gA);vTr","=i/s*dG,l=cos(r),h=sin(r),a=gA(r);%5c'nbT%5c'cVa?gE*luBa*h):gE[0","]uBa[1]),lDi]=t+o.gAYlXlDi]uBe+o.gAXlXgLxp[ioQi]=n*lzTi]=n*h,lY[","i]=pW[i]=kT[i]=T(256)}u||gLbK(),s=gLkC}}}qFetcM)=>ro(mS)cAot=t=>","ro(aHt,255))),ituR%5c'cD0%5c'+(65536*ot(t)+256*ot(e)+ot(i)).toSq","R(16);tJ%5c'%23%5c'+r.subsqR(rbB-6)};toTqIwRgLyp,euQ,i=gLyv,r=gL","xv,s=lY,h=pW,a=kT,u=gLkC,p=tK,d=p[u],c=W(mxuN,u-o.vB),dAceil(d/o",".iA),mn(u+o.vB,o.maxcS)),f=d/c;gLypmDxpmDyvmDxvmDredbLpWbLkTbLgL","kC=cfXv=0lBc;n++sXl=n*f;for(;qH<l;)v++fXd=(v+1)%25u,c=qH-p[v],b=","(l-p[v])/c;lDn]=tjOt[d]sFn]=ejOe[doQn]=ijOi[d]zTn]=rjOr[d],lY[n]","=sjOs[d],pW[n]=hjOh[d],kT[n]=ajOa[d]}vSeIdisplayText(this),d}cAs","qr=t=>t*t;toTbKwRo.vB;o.vB=lZqI(),o.vB=tfAmWwRtK;vSrNfAdVwRgLkC,","e=nnH;e[0]=0;kKi=0;i<t;i++sXhZ%25t,scXlDr]-lDi]sFrbAi]);e[i+1]=e","[i]+s}vSefArYtPpGgLkC;s++)lDs]=W(i,lDs],r)sFs]=W(tsFs],e)}cArtmQ",",staOname,gS){gLclicks=[],gLname=name,wO=uYfXs=.7+.6*cR(xQ;wO[e]","=1+.3*(xN5*i*s)+xN7*i*s+.3))}lY=e,pW=i,kT=r,qMgDpHLabelpY};soTwD","wRoowL*wOnE(h);vSpKBitwL?0<t:uCwL?dAround(t)||1:t||ptsRaGnEhBt/d","G*wObB;(e%25aQ<0&&(e+aQfXisW(e),hZ%25wObB,s=e-i;vSwO[yAi)]*(1-s)","+s*wO[r]sRcoloraO){vSit(lY,pW,kT)sRvIwRwObB;qM||(qM=vt(t)xQ-h,r=","vZOfZeroOption+vZMul*wO[e];qM.xqVsinvEyqVcosvEred[e]=lY,qMpT[e]=","pW,qM.blue[e]=kT}}cAnt=dE=>{kKtcIsXn=lR;oI&&nmF,oI=(oI||0)+1}kKl","cI)if(!n||l==tsXt=oL[l];t.vI(),t.curve.eYtmF}},htxLgC){qMs=t,gLw","C=e,gLqS=i,gLiI=r,gLgCpY};hoTtyLwR0;aIqMsbBiZ+=qMs[e].dt;vSt}cAa","tmT0,r=e-t;if(r>0)i+=r*r*o.uV;else{i+=10*(lK*(e/t))-lK))}vSi},nV","xIo.nV)xVnVmV%5c'nV=%5c'+nVcAut=(nQ,nNkFccXi-t,r-e),en=0xVo.vW){","o.aVfXscXt-a,e-u);dAhypot(i-a,r-u);en=vU+vU}vSen=nV(en,c,d)},pt=","1e-6,dt={iXY:0,iXX:0,aG:1},ctbH-.1+X(),fcQ[];aILbB-1iZtZyVL[e],L","[e+1]],ct));vSk(t),t},vt=t=>mJvoid%200,pt,ut,gJ0nOt,ft(),N,!0),b","cQft();vSnew%20ht([vtuN)],ut,t,N,null)},ytbH{pUeIclearLoops()},o","L={},mtbH{adjustBordersOfOppF(oo)},xtkJeI(putInDefaults(oo),o=e(","oo)),!uP%5c'no%20nV%5c';zZ(oo.chE),h=0,yt(),Pt=[bt()];gYo.oL)nAo",".lRbB,!0);o.rO&&fS(o.rO),eI(t=oL.tyL?%5c'tyL%5c':null,Z(%5c'gAEd","itor%5c').value=o.gA)},Mt=0,Pt=[],wtbHPt[0],St=H(),AcQwt(),e=H()",",iyGe-St,.1);h+=2*i*dAPI/o.iO,(h%25=dG)<0&&(h+=dG),s()fXr=0tNkVX","e=o.tyL-t.tyL();ryGo.gT,1)*i*e}wIr=i*o.tkP;r*yGoo.tF,1),St=e,c=c","*(1-i)+1fXn=r<0,l=r,a=r;for(fWn&&(Mt=0);Mt<tkXbB-3&&fWr<0;)Mt++,","l=a,a=r,r+jQnXMt].dt)fXu=nX1-Mt]tNjP&&(r=mx(0,r)),!u)tJfXp=u.kCm","CrsXe=mJu,r,t.wC,gJo.gCnOp,t.qS,t.iI);o.qI&&e.qI()fXi=1/(1-W(0,o",".gX,.95));e.rY(-i,i,-i,i),tkXtZe)}tkXbB>o.vF&&(tkX=tkX.slice(-o.","vF))},Ct=(nQkFa=e.vRbB>0,u=t&&!a,p=aPkC,c=0,f=t=>e.vRtZt);iCdbOa","=nH%25d,vlEt]),brQt]),ylEa]),mrQa]),x=y-v,g=m-b;c=mx(c,g*g+x*x)f","XM=o.oC,P=o.pR,w=(e.redwERed+P,S=(epTwEkU+P,A=(e.bluewEBlue+PtNh","W||(w=ot(w),S=ot(S),A=ot(A)),u&&iqQ(f,b,v,m,y,w,S,A,h),!pmV%5c'!","bM%5c'}p&&i.bM(e.vR)},pUFtgDDt=(kFe=wt()cAi=Z(%5c'aDiv%5c');ekX[","ekXbB-1];p=0,a=0,d=wyCrH,u=wyCWidthfXr=(d+p)/2,s=(u+a)/2,njQ(1-o",".gX)*mn(d-p,u-a)/2),l=n,h=r+%5c'_%5c'+s+%5c'_%5c'+n+%5c'_%5c'+l;","Ft!=h&&setTimeoutvDBt=Rt=!0},200),Ft=h,eI%5c'%5c'!=bI&&(bI=%5c'%","5c')fXc=Rt;a+10<u&&p+10<d&&J.iK(nN)fXrU;!Rt&&o.tD||(RzEJ.eG(),rU",");kKt=y;t<J.yFbB;t+=4)m[t]=255xVcsXt=Bt||!o.tD;if(BzEt)if(sLqW)q","W(o.mB,o.bwYkU,o.dZ,o.bpJ,KrF0,1024,J.yF,fl(rmNr+2*n),fl(smNs+2*","l));eXt=m.b,esKRed),isKkU),rsKBlue);pGtbB;s+=4)t[s+f]=ezNv]=izNb","]=rzNbXlet%20i=o.oV,hvCif(ijB){for(;ekXbB>2jB;sXtvCCt(i,tjDMt--}","Mt=0}ekXtZh),Ct(i,hjDeIfGtryDispOutCirc(rbJ)}if(bxEsXe=Z(%5c'chk","OnlyPaintSelectedLoop%5c').checked;fGoFnt(rbJ,e);kKicI){!(oF(!e|","|i==t))&&jH&&(jH.zY(),delete%20jH)}fGo.xY&&xY()}J.aJ()},OzEXt=0,","VtbH{Xt++cAt=!0tNpause||o.tF<=0)t=!1;eXtX(1/o.tF);t=Xt%25e==0}t&","&(At(),Dt()),requestAnimationFrame(Vt)},TtpY;wi.onload=vDOt=!0yK","BxE(),Tt=Z(%5c'divabxy%5c'),J||(JnYx(Tt)),xt(),Vt()});';let%20re","place='this.@gL@=function(@aO@for(let%20@kK@maxNumPointsPerCurve","ChangeAtOnce@vB@maxDistanceToAffectEachother@uI@.length@bB@pseud","orandomFraction@cR@){let%20@sX@t.prototype.@oT@rightMult@pJ@imeP","osition@yL@balanceSparsity@qI@bootShape@gA@return%20@vS@addRando","mness@gC@PointsPerCurve@cS@ttractIfFartherThan@yH@=Math.@cN@[t]*","(1-M)+255*M)*o.paintBpJ*o.bpJ@wE@midDist*p.bell@eJ@ndoable2dVoxe","l@uM@)=>{let%20@kF@[v]*(1-b)+b*@jO@numPoints@kC@Mul:[1.088,0.@vP","@t,e,i,r@gS@.curves@kX@rightAdd@wY@kKe=0;e<@aI@gLradius@wO@build","er&&@eI@undoableVoxels@vR@accelFieldMul@fB@Math.floor(@yA@=ot(12","7.5+127.5*M.arr[@kS@M.voxel@hX@targetDistanceBetweenAdjacentCurv","ePoints@iA@aOgS,ssXn=W(0,4*(yAt)*gLw+yAe)),gLbbB-4)@aY@negTimeDo","esUndo@jP@otentialEnergyF@aS@loops[t]@lR@,J.byteRect,r,s,n,l,mx(","1,o.lineThick)),@jD@,a,p,f,v,d,c,m,s)*x,@iH@gLcurve@qM@;%20x%20+","=%20sin(m*p.freq@fI@kKt=0;t<@iC@cNhypot(@cX@displayOuterCircle@p","Q@perimeterDistances@dV@yp[l],gLxp[l]@hU@=t=>JSON.parse(JSON.str","ingify(t))@mQ@;let%20@fX@loops[i].domLabel@jH@setSpeedsToZeroAft","erEveryDtMove@mE@endist@nV@;const%20@qF@gLgreen@pW@optionIs@pK@c","omputeSpeed@tF@maxCurvesPerReef@vF@.streamUuMsForLineYXYXRGBSafe","@qQ@;var%20@cA@:true,@sT@stayInsideBorderCircleForce@uV@graphEnd","ist@xY@gLimageData@aT@(0,512+256*@fF@Height,dist);%20x%20+=%20be","ll(eJ@oD@);aIt;e++sXi=2*Math.PI*e/t@xQ@byteRect@yF@void%200===@v","J@writeSafe@fR@borderFraction@gX@chkBuilder()&&@fG@sliderOrCheck","boxValueNow@wD@.paintOrUnpaint(e,i,r,s)@mF@DevMul,p.bell@aB@,gLd","om.height@oJ@n.countPaints@oI@ifCanvasUseUndoGraphics@oV@,o.maxS","peed,o.friction,@nO@[i]/127.5-1,t.arr[3*e+@qE@copyRadiusArrayToC","urve@vI@Math.@dA@gLyp[@lD@gLblue@kT@,gLxp[@sF@resizeCanvas@iK@[l","]*(1-A)+A*@yU@i.inner@yC@gLcontext@gH@,bell@oG@new%20Float32Arra","y(t)@uY@accelVoxels@rO@gLdom.width@qZ@beforePaint@eG@paintVoxels","@bM@=t=>{let%20e=@rC@)throw@mV@=null,@gD@gLb[n+@fV@sizes[@vO@aOs","Xt=@wR@:false,@nT@bB;t++)@pV@;if(0!=@mC@gLyv[l]@aC@gLxv[l]@oU@am","pStraightIfNear@kD@n)&((1n<<48n)-1n)@dN@olorSeed@hE@=n(s),gL@fU@","=n(c),gL@mD@:[1.088,1.@dX@gS,s,n,l,h@nQ@colorDecayPerSec@wM@pseu","dorandomNext@fM@,e.yp[t],e.xp[t]@dU@=()=>@bH@borderRadiusMul@kY@","l.setAttribute(@cC@kKi=0;i<s;i++sX@vT@paintAccelField@qW@AveMul@","hK@Height@rH@isSurface@tD@,0.912,0.@bU@pKInteger@uC@==typeof%20@","cV@else{let%20@eX@%20in%20loops@cI@=ot(o.bwY@sK@(sin(a*3)+sin(@o","E@window.@sL@sigmoid@jT@midDist@wH@aintBpJ@sU@seed[0]@nL@=(t,e,i","@cM@distanceScale@aV@sameColorness@oC@gLarr=l(R(t))@gN@mx(t,mn(e",",i))@mS@neuralWeights@qS@=ro(s+l*e.xp[@lE@=ro(r+n*e.yp[@rQ@;%20l","et%20@aM@.push(@tZ@],t[e+@lN@imeSpeed@kP@friction@pX@maxSpeed@cK","@kKt%20in%20o@gY@gLpixels@kB@aItbB;e+@wA@mx(0,mn(@aH@[gLname]@wL","@scalePaSorce@eV@console.log(@uU@performance.@xZ@Rt=!0,Bt=!0,@pU","@loopSeconds@iO@0x5DEECE66D@zO@tImageData(@rJ@&255),hXXor@wQ@hXY","XXorsRGB@wZ@(e,i,r,s,n)@dE@=0;kKl=0;l<@zH@=2*cR()-1)*@sQ@xp[l]-p",".xp[@cF@+=o.fB*B*F.@eF@+o.gAScale*@lX@=ekX.pop();@vC@Green@kU@lo","ops@oL@gLred@lY@%20x%20+=%20@zP@radius@aG@gLb[l+@eP@center@iX@=l","(s),@kA@.green@pT@;if(o.@tN@DevMul:@rG@)*p.amp@uW@new%20B([@yV@]","-gLxp[@bA@dAabs(i@oA@t=(kFt=@cQ@*sqr(dist-@cO@onlyEndist@vW@=mx(","10,wyC@iQ@afterPaint@aJ@.prototype@cG@=(t=>fl(t/@eD@dAexp(-.5*@b","Z@,1023.99),@dW@]cNtanh(K[@mK@holdInRect@rY@loopRadius@vZ@neural","Func@iI@new%20tt(!1,@mJ@tkX[tkXbB-@nX@twoPi@dG@,0.62@gV@gLdom@pH","@,0.544,0.@wJ@:1.01,bpJ@bC@nearPdist@nZ@,1.115,1.@wF@,1.123,0.@d","F@repelSelf@eU@bits1To32@jN@document.@iE@ceil(1.5*@rZ@;kKn=0;n<@","lB@Xt=0,e=0,@pE@=(t,ekFi=@mT@=-r*((V(p@mX@)-c)/pt),@lJ@perimeter","@mW@[t]=0==n?@xX@(i)*r,qM.@vE@-2*l),fl(@mN@7,0.7@hM@9,0.9@hI@7,1",".0@iT@00000@cD@;if(!@xV@:0.01,@dI@uilder@xE@BigInt@uT@,s,n,l@bJ@","+px,h.@yY@=hXXor@nW@;e++sX@bW@arr[t]@hQ@t.vO1]@hC@;e++)t@iZ@=eva","l(@xI@return@tJ@;t++sX@bO@=l(c),@bL@,0.1,0,0@kZ@GeneReef@jU@pain","tBwY@pR@tyLDecay@gT@pKBit[t]@fN@lR=r(t,o@nA@)&S),hXX@uG@=(t=>t>>","@uJ@fRXorRGB@hN@(t[e])},@vY@putHills@fS@)/256/i,@iP@l]-p.yp[@bR@","]=p.blue@mM@t[tbB-1]@rN@(o.mincS@uN@kKs=0;s<@pG@,0,1024,@rF@39,1",".@hH@8,0.7@wS@,0.98@mU@,0.97@vV@26,0.@kM@28,0.@cP@,1.01@lV@,1.33","@dO@72,0.@iD@08,1.@vG@,1.32@qX@umber@bT@=W(0,@yG@=null@pY@bwYBlu","e@dZ@dist)aM@xO@,0.605,@sG@,maxcS:@bV@,mincS:@gR@useTyLs@kV@wrap","PsU@hW@64Array@cW@=>{nL=(@lL@retLong@tQ@,eIboot@yK@cNfloor@sW@ec","Nceil@tX@Element@yJ@.style;@mG@aOtsXe=@hB@y]=255}@bX@.matmul@qN@","gLvO0],@eN@cNsqrt(@gU@]=p.red@pL@=r(gLhU@eA@(lDi]=a@gE@],gLyv[@o","Q@r=(i+1)@hZ@AtAngle@nE@jT(.001@lK@a,u,p,d@nN@at(p,s)@vU@anvas@s","N@hK,eJ@cL@tions@pF@9,-0.@iR@AvevP@uO@9,0.7@pN@DevvP@tH@,0.52@tL","@9,1.4@qG@,1.11@lT@4,0.4@zR@,1.03@cZ@,1.07@eB@56,0.@sC@2,1.1@aA@","98,0.@rW@tring@qR@o[t]=@hG@=i(),@zG@=new%20@nY@aOt){@jF@aOgS,@xL","@(gS,s@jZ@gLarr@mP@else%20@wI@=t=>{@sS@o.uI,@gJ@(t+1)@nH@=gLxp@u","Q@sFi]=@uB@},toT@fA@},soT@sR@t=!1,@zE@,t[s+@zN@ampAyH@eE@bwYRed@","mB@o.ayH)@jY@dAsqrt@uF@02,2.1@fK@0.421,@jL@V4,0.8@oY@setChE@zZ@o",".nVmV@uP@1e6,gL@lZ@aOgS){@tP@=0),vJ@eQ@height@hP@aO){gH@oP@,mx(1","0@pZ@cNpow(@wV@cMkFr=@uR@bH{if(@kJ@,1023)@xJ@]/b+c*@qO@remove@zY","@t,d=e.@aP@vR=[],@eY@-M)/pt@fQ@,gLxv[@zT@qIBoot@bK@gLdV()@tK@p[v","+1]@qH@dAsin(@xN@=wObB)@aQ@p[e]cN@qV@paSunc@wC@o.jP&&@fW@cNabs(@","jQ@(()=>{@vD@yCHTML@bI@m=J.yF@rU@&&Mt>0@jB@o.pQ&&@oF'.split('@')",";for(let%20i=replace.length-2;%20i>=0;%20i-=2)%20code%20=%20code",".split(replace[i+1]).join(replace[i]);console.log(code);eval(cod","e);</script></head><body%20style='background-color:black;color:w","hite;user-select:none'><div%20id=divabxy%20style='background-col","or:black;color:white;width:0px;height:0px'></div></body></html>"]}],"geneReefId":"44","image":"ipfs://QmdBYWqvXrsR4D36aGAb2sja8fTcY4nyCnnKJJFGYjUTSn","mediaType":"image/jpeg","species":"19","startingShape":"21"}}}}